gravpy/__init__.py
gravpy/newtonian.py
tests/__init__.py
gravpy_core-0.1.0.dist-info/METADATA
gravpy_core-0.1.0.dist-info/WHEEL
gravpy_core-0.1.0.dist-info/top_level.txt
gravpy_core-0.1.0.dist-info/RECORD
