Metadata-Version: 2.1
Name: gravpy-core
Version: 0.1.0
Author: javi22020
Requires-Dist: numpy
